azure/mgmt/appplatform/__init__.py
azure/mgmt/appplatform/_app_platform_management_client.py
azure/mgmt/appplatform/_configuration.py
azure/mgmt/appplatform/_patch.py
azure/mgmt/appplatform/_serialization.py
azure/mgmt/appplatform/_version.py
azure/mgmt/appplatform/py.typed
azure/mgmt/appplatform/aio/__init__.py
azure/mgmt/appplatform/aio/_app_platform_management_client.py
azure/mgmt/appplatform/aio/_configuration.py
azure/mgmt/appplatform/aio/_patch.py
azure/mgmt/appplatform/aio/operations/__init__.py
azure/mgmt/appplatform/aio/operations/_api_portal_custom_domains_operations.py
azure/mgmt/appplatform/aio/operations/_api_portals_operations.py
azure/mgmt/appplatform/aio/operations/_apms_operations.py
azure/mgmt/appplatform/aio/operations/_application_accelerators_operations.py
azure/mgmt/appplatform/aio/operations/_application_live_views_operations.py
azure/mgmt/appplatform/aio/operations/_apps_operations.py
azure/mgmt/appplatform/aio/operations/_bindings_operations.py
azure/mgmt/appplatform/aio/operations/_build_service_agent_pool_operations.py
azure/mgmt/appplatform/aio/operations/_build_service_builder_operations.py
azure/mgmt/appplatform/aio/operations/_build_service_operations.py
azure/mgmt/appplatform/aio/operations/_buildpack_binding_operations.py
azure/mgmt/appplatform/aio/operations/_certificates_operations.py
azure/mgmt/appplatform/aio/operations/_config_servers_operations.py
azure/mgmt/appplatform/aio/operations/_configuration_services_operations.py
azure/mgmt/appplatform/aio/operations/_container_registries_operations.py
azure/mgmt/appplatform/aio/operations/_custom_domains_operations.py
azure/mgmt/appplatform/aio/operations/_customized_accelerators_operations.py
azure/mgmt/appplatform/aio/operations/_deployments_operations.py
azure/mgmt/appplatform/aio/operations/_dev_tool_portals_operations.py
azure/mgmt/appplatform/aio/operations/_gateway_custom_domains_operations.py
azure/mgmt/appplatform/aio/operations/_gateway_route_configs_operations.py
azure_mgmt_appplatform-10.0.1.dist-info/LICENSE
azure_mgmt_appplatform-10.0.1.dist-info/METADATA
azure_mgmt_appplatform-10.0.1.dist-info/WHEEL
azure_mgmt_appplatform-10.0.1.dist-info/top_level.txt
azure_mgmt_appplatform-10.0.1.dist-info/RECORD
